[{"input":false,"tableView":false,"key":"initSendAppReadyEmail","label":"initSendAppReadyEmail","protected":false,"unique":false,"persistent":false,"linked":{"inputs":[null],"outputs":["pluginSendAppReadyEmail",null]},"initializerData":{"dataInputObject":[],"dataOutputObject":[{"id":"pluginSendAppReadyEmail","type":"trigger","value":"GO"}]},"triggerType":"edit","type":"initializer","creator":"unqorkgsuite_mark.wiedmann@unqork.com","created":"2020-09-24T16:58:08.229Z","modifier":"unqorkgsuite_mark.wiedmann@unqork.com","modified":"2020-09-24T20:17:09.296Z","ancestors":["root"],"watcherList":[],"wasDropped":true,"$$hashKey":"object:49708"},{"multiple":true,"input":true,"tableView":true,"key":"pluginSendAppReadyEmail","label":"pluginSendAppReadyEmail","protected":false,"unique":false,"persistent":false,"linked":{"inputs":["submissionId","clientFirstName","clientLastName",null],"outputs":[null]},"integratorData":{"dataTestObject":[],"dataInputObject":[{"id":"submissionId","mapping":"data.subId","required":false,"exclude":false,"header":false,"resolveBase64":false,"optional":false},{"id":"clientFirstName","mapping":"data.clientFirstName","required":false,"exclude":false,"header":false,"resolveBase64":false,"optional":false},{"id":"clientLastName","mapping":"data.clientLastName","required":false,"exclude":false,"header":false,"resolveBase64":false,"optional":false}],"dataOutputObject":[],"dataFrame":[],"integratorUrl":"/fbu/uapi/modules/5f6cfdb985a56f024db5b7a3/execute"},"triggerType":"manual","serviceType":"unqork","requestType":"put","topLevelArray":false,"arrayKeyPromote":"","assignEmptyValues":true,"unqorkApi":"/modules/{moduleId}/execute:put","service":null,"preRequestTransform":null,"prefix":"","type":"integrator","allowSingleRecordArray":true,"doNotLookForDataKeyInResponse":true,"creator":"unqorkgsuite_mark.wiedmann@unqork.com","created":"2020-09-24T16:56:11.127Z","modifier":"unqorkgsuite_mark.wiedmann@unqork.com","modified":"2020-09-25T19:30:16.913Z","ancestors":["root"],"watcherList":[],"$$hashKey":"object:49709"}]